fckitlib/__init__.py
fckitlib/bin/fckit
fckitlib/include/fckit/Log.h
fckitlib/include/fckit/Main.h
fckitlib/include/fckit/fckit.h
fckitlib/include/fckit/fctest.h
fckitlib/lib/libfckit.dylib
fckitlib/lib/cmake/fckit/fckit-config-version.cmake
fckitlib/lib/cmake/fckit/fckit-config.cmake
fckitlib/lib/cmake/fckit/fckit-import.cmake
fckitlib/lib/cmake/fckit/fckit-targets-relwithdebinfo.cmake
fckitlib/lib/cmake/fckit/fckit-targets.cmake
fckitlib/module/fckit/array.mod
fckitlib/module/fckit/fckit_array_module.mod
fckitlib/module/fckit/fckit_buffer_module.mod
fckitlib/module/fckit/fckit_c_interop_module.mod
fckitlib/module/fckit/fckit_configuration_module.mod
fckitlib/module/fckit/fckit_exception_module.mod
fckitlib/module/fckit/fckit_final_module.mod
fckitlib/module/fckit/fckit_log_module.mod
fckitlib/module/fckit/fckit_main_module.mod
fckitlib/module/fckit/fckit_map_module.mod
fckitlib/module/fckit/fckit_module.mod
fckitlib/module/fckit/fckit_mpi_module.mod
fckitlib/module/fckit/fckit_object_module.mod
fckitlib/module/fckit/fckit_owned_object_module.mod
fckitlib/module/fckit/fckit_pathname_module.mod
fckitlib/module/fckit/fckit_refcount_module.mod
fckitlib/module/fckit/fckit_resource_module.mod
fckitlib/module/fckit/fckit_shared_object_module.mod
fckitlib/module/fckit/fckit_shared_ptr_module.mod
fckitlib/module/fckit/fckit_signal_module.mod
fckitlib/module/fckit/fckit_tensor_module.mod
fckitlib/module/fckit/fckit_test_abort.mod
fckitlib/module/fckit/fckit_test_abort_fx.mod
fckitlib/module/fckit/fckit_test_log.mod
fckitlib/module/fckit/fckit_test_resource.mod
fckitlib/module/fckit/fckit_test_shared_ptr_f.mod
fckitlib/module/fckit/fcta_functionspace.mod
fckitlib/module/fckit/fcta_functionspace_fxt.mod
fckitlib/module/fckit/fcta_shared_ptr_f_fxt.mod
fckitlib/module/fckit/fcta_tensor_f_fxt.mod
fckitlib/module/fckit/fctest.mod
fckitlib/module/fckit/fctest_fckit_configuration.mod
fckitlib/module/fckit/fctest_fckit_configuration_fails.mod
fckitlib-0.14.0.4.dist-info/licenses/LICENSE
fckitlib-0.14.0.4.dist-info/METADATA
fckitlib-0.14.0.4.dist-info/WHEEL
fckitlib-0.14.0.4.dist-info/top_level.txt
fckitlib-0.14.0.4.dist-info/RECORD
