Metadata-Version: 2.4
Name: fckitlib
Version: 0.14.0.4
Summary: "fckitlib"
Author: file: AUTHORS
License-File: LICENSE
Requires-Dist: eckitlib==1.32.2.4
Dynamic: license-file
Dynamic: requires-dist
